<?xml version="1.0" encoding="utf-8"?>
<odoo>
    <data>
        
        <!-- Configuración DGI con datos reales de Pastas Frescas -->
        <record id="real_dgi_config" model="dgi.config">
            <field name="company_id" ref="base.main_company"/>
            <field name="ruc">11703330</field>
            <field name="dv">5</field>
            <field name="company_name">Pastas Frescas, S.A.</field>
            <field name="commercial_name">Pastas Frescas</field>
            <field name="address">Calle Avenida 8A Norte Calle 64 Oeste, Edificio Mas Espacio, Local 3, Urbanización Industrial Los Angeles, Panama City, Panamá</field>
            <field name="phone">+507 200-0000</field>
            <field name="email">contabilidad@pastasfrescas.com</field>
            <field name="pac_provider">the_factory_hka</field>
            <field name="pac_username">byxyhbmumrxv_tfhka</field>
            <field name="pac_password">m:v*0aU+3L5d</field>
            <field name="pac_url">https://demoemision.thefactoryhka.com.pa/ws/obj/v1.0/Service.svc?wsdl</field>
        </record>
        
    </data>
</odoo>
